{
  "culture": "pt-BR",
  "texts": {
    "Menu:Home": "Início",
    "Welcome": "Bem-vindo",
    "MensajeWelcome": "Bem-vindos ao Paws & Whiskers",
    "LongWelcomeMessage": "Paws & Whiskers nasceu de uma paixão compartilhada pelos fundadores: o amor por animais de estimação e a falta de uma plataforma que oferecesse tanto produtos de alta qualidade quanto uma experiência de compra personalizada e amigável ao meio ambiente. Em um mercado saturado de opções, percebemos uma clara necessidade de uma loja online que não apenas vendesse produtos para animais de estimação, mas também compreendesse e priorizasse as necessidades individuais de cada animal e seus donos.",
    "Enum:ProductoType.0": "Comida",
    "Enum:ProductoType.1": "Brinquedo",
    "Enum:ProductoType.2": "Equipamento",
    "Enum:MascotaType.0": "Cachorro",
    "Enum:MascotaType.1": "Gato",
    "ProductoType": "Tipo de produto",
    "MascotaType": "Tipo de animal de estimação",
    "Price": "Preço",
    "CreationTime": "Hora de criação",
    "Menu:Cesta": "Loja",
    "Menu:Carrito": "Carrinho",
    "Menu:CRUDProductos": "Gerenciamento de produtos",
    "NewProducto": "Adicionar produto",
    "ProductoDeletionConfirmationMessage": "Tem certeza de que deseja excluir este produto?",
    "ProductoEditedSuccesfully": "Produto editado com sucesso",
    "ProductoErasedSuccesfully": "Produto excluído com sucesso",
    "ProductoCreatedSuccesfully": "Produto criado com sucesso",
    "Menu:Productos": "Produtos",
    "Permission:Cesta": "Permissões no catálogo",
    "Permission:Productos": "Permissões nos produtos",
    "Permission:Productos.Create": "Criar produtos",
    "Permission:Productos.Edit": "Editar produtos",
    "Permission:Productos.Delete": "Excluir produtos",
    "FinalizarCompra": "Finalizar compra",
    "NoPedidos": "Aqui você encontrará os produtos que adicionou ao carrinho",
    "NoProductosEnCatalogo": "Não há produtos no catálogo no momento",
    "IrCatalogo": "Ir para o catálogo",
    "UnexpectedError": "Ops, algo deu errado",
    "formatoImagenMalo": "O formato do arquivo não é válido",
    "EliminarDeCesta": "Excluir",
    "VolverCatalogo": "Voltar",
    "Total": "Total",
    "NecesitasInicioSesion": "Você não está logado",
    "esPagoSeguro": "Este método de pagamento é seguro?",
    "politicaCookies": "Política de cookies",
    "Edit": "Editar",
    "Name": "Nome",
    "Direccion": "Endereço",
    "InserteDireccion": "Por favor, insira um endereço",
    "Cancel": "Cancelar",
    "Submit": "Enviar",
    "Confirm": "Confirmar",
    "EstasSeguro": "Você tem certeza?",
    "CancelConfirmation": "Tem certeza de que deseja cancelar?",
    "YesCancel": "Sim, cancelar",
    "NoCancel": "Não, voltar",
    "Cancelled": "Cancelado",
    "CanceladoProceso": "Você cancelou o processo",
    "HasComprado": "Você confirmou sua compra com seu cartão {0} no endereço {1} para entrega em {2}",
    "CestaSinInicioSesion": "Para acessar esta página, você precisa estar logado",
    "InserteDatosEntrega": "Dados de entrega",
    "FechaEntrega": "Data de entrega",
    "InserteFecha": "Por favor, insira uma data",
    "CompraRealizada": "Compra realizada com sucesso",
    "EnviarCorreo": "Enviar e-mail"
  }
}
